{
    "apiVersion": 2,
    "name": "excelsior-bootstrap/accordion-item",
    "title": "Accordion Item",
    "category": "excelsior-bootstrap-blocks",
    "parent": ["excelsior-bootstrap/accordion"],
    "icon": "minus",
    "supports": {
        "html": false
    },
    "attributes": {
        "title": {
            "type": "string",
            "default": "Accordion Item"
        },
        "content": {
            "type": "string",
            "default": ""
        }
        },
    "editorScript": "file:./index.js"
}